{
	"dimension": {
		"$type": "dimension",
		"primitive": {
			"space": {
				"0": {
					"$value": { "value": 0, "unit": "px" },
					"$description": "Empty space"
				},
				"10": {
					"$value": { "value": 4, "unit": "px" },
					"$description": "1x base spacing"
				},
				"20": {
					"$value": { "value": 8, "unit": "px" },
					"$description": "2x base spacing"
				},
				"30": {
					"$value": { "value": 12, "unit": "px" },
					"$description": "3x base spacing"
				},
				"40": {
					"$value": { "value": 16, "unit": "px" },
					"$description": "4x base spacing"
				},
				"50": {
					"$value": { "value": 20, "unit": "px" },
					"$description": "5x base spacing"
				},
				"60": {
					"$value": { "value": 24, "unit": "px" },
					"$description": "6x base spacing"
				},
				"70": {
					"$value": { "value": 32, "unit": "px" },
					"$description": "8x base spacing"
				},
				"80": {
					"$value": { "value": 40, "unit": "px" },
					"$description": "10x base spacing"
				},
				"90": {
					"$value": { "value": 48, "unit": "px" },
					"$description": "12x base spacing"
				}
			}
		},
		"semantic": {
			"base": {
				"$value": "{dimension.primitive.space.10}",
				"$description": "Base dimension unit"
			},
			"padding": {
				"surface": {
					"2xs": {
						"$value": "{dimension.primitive.space.10}",
						"$description": "2x extra small spacing for surfaces",
						"$extensions": {
							"mode": {
								"compact": "{dimension.primitive.space.10}",
								"comfortable": "{dimension.primitive.space.20}"
							}
						}
					},
					"xs": {
						"$value": "{dimension.primitive.space.20}",
						"$description": "Extra small spacing for surfaces",
						"$extensions": {
							"mode": {
								"compact": "{dimension.primitive.space.10}",
								"comfortable": "{dimension.primitive.space.30}"
							}
						}
					},
					"sm": {
						"$value": "{dimension.primitive.space.40}",
						"$description": "Small spacing for surfaces",
						"$extensions": {
							"mode": {
								"compact": "{dimension.primitive.space.30}",
								"comfortable": "{dimension.primitive.space.50}"
							}
						}
					},
					"md": {
						"$value": "{dimension.primitive.space.60}",
						"$description": "Medium spacing for surfaces",
						"$extensions": {
							"mode": {
								"compact": "{dimension.primitive.space.50}",
								"comfortable": "{dimension.primitive.space.70}"
							}
						}
					},
					"lg": {
						"$value": "{dimension.primitive.space.70}",
						"$description": "Large spacing for surfaces",
						"$extensions": {
							"mode": {
								"compact": "{dimension.primitive.space.60}",
								"comfortable": "{dimension.primitive.space.80}"
							}
						}
					}
				}
			}
		}
	}
}
